forum/__init__.py
forum/account.py
forum/threads.py
forum/user.py
forum/ext/__init__.py
forum/ext/driver.py
forum/ext/errors.py
forumpy-0.0.3.dist-info/METADATA
forumpy-0.0.3.dist-info/RECORD
forumpy-0.0.3.dist-info/WHEEL
forumpy-0.0.3.dist-info/top_level.txt
