Metadata-Version: 2.1
Name: forumpy
Version: 0.0.3
Summary: An unofficial SA-MP forum api
Home-page: https://github.com/sreyas-sreelal/forum-py
Author: Sreyas Sreelal
Author-email: sreyassreelal@gmail.com.com
License: UNKNOWN
Platform: UNKNOWN
Classifier: Programming Language :: Python :: 3
Classifier: License :: OSI Approved :: GNU General Public License v3 (GPLv3)
Classifier: Operating System :: OS Independent
